8a4082216e5922611c62__mypyc.cp310-win_amd64.pyd
8a4082216e5922611c62__mypyc.cp311-win_amd64.pyd
8a4082216e5922611c62__mypyc.cp312-win_amd64.pyd
8a4082216e5922611c62__mypyc.cp313-win_amd64.pyd
8a4082216e5922611c62__mypyc.cpython-310-darwin.so
8a4082216e5922611c62__mypyc.cpython-310-x86_64-linux-gnu.so
8a4082216e5922611c62__mypyc.cpython-311-darwin.so
8a4082216e5922611c62__mypyc.cpython-311-x86_64-linux-gnu.so
8a4082216e5922611c62__mypyc.cpython-312-darwin.so
8a4082216e5922611c62__mypyc.cpython-312-x86_64-linux-gnu.so
8a4082216e5922611c62__mypyc.cpython-313-darwin.so
8a4082216e5922611c62__mypyc.cpython-313-x86_64-linux-gnu.so
dank_mids/ENVIRONMENT_VARIABLES.cp310-win_amd64.pyd
dank_mids/ENVIRONMENT_VARIABLES.cp311-win_amd64.pyd
dank_mids/ENVIRONMENT_VARIABLES.cp312-win_amd64.pyd
dank_mids/ENVIRONMENT_VARIABLES.cp313-win_amd64.pyd
dank_mids/ENVIRONMENT_VARIABLES.cp314-win_amd64.pyd
dank_mids/ENVIRONMENT_VARIABLES.cpython-310-darwin.so
dank_mids/ENVIRONMENT_VARIABLES.cpython-310-x86_64-linux-gnu.so
dank_mids/ENVIRONMENT_VARIABLES.cpython-311-darwin.so
dank_mids/ENVIRONMENT_VARIABLES.cpython-311-x86_64-linux-gnu.so
dank_mids/ENVIRONMENT_VARIABLES.cpython-312-darwin.so
dank_mids/ENVIRONMENT_VARIABLES.cpython-312-x86_64-linux-gnu.so
dank_mids/ENVIRONMENT_VARIABLES.cpython-313-darwin.so
dank_mids/ENVIRONMENT_VARIABLES.cpython-313-x86_64-linux-gnu.so
dank_mids/ENVIRONMENT_VARIABLES.cpython-314-darwin.so
dank_mids/ENVIRONMENT_VARIABLES.cpython-314-x86_64-linux-gnu.so
dank_mids/ENVIRONMENT_VARIABLES.py
dank_mids/__init__.py
dank_mids/_batch.cp310-win_amd64.pyd
dank_mids/_batch.cp311-win_amd64.pyd
dank_mids/_batch.cp312-win_amd64.pyd
dank_mids/_batch.cp313-win_amd64.pyd
dank_mids/_batch.cp314-win_amd64.pyd
dank_mids/_batch.cpython-310-darwin.so
dank_mids/_batch.cpython-310-x86_64-linux-gnu.so
dank_mids/_batch.cpython-311-darwin.so
dank_mids/_batch.cpython-311-x86_64-linux-gnu.so
dank_mids/_batch.cpython-312-darwin.so
dank_mids/_batch.cpython-312-x86_64-linux-gnu.so
dank_mids-4.20.192.dist-info/METADATA
dank_mids-4.20.192.dist-info/WHEEL
dank_mids-4.20.192.dist-info/licenses/LICENSE
dank_mids-4.20.192.dist-info/RECORD
