Metadata-Version: 2.4
Name: dank-mids
Version: 4.20.192
Summary: Multicall batching middleware for asynchronous scripts using web3.py
License: MIT
License-File: LICENSE
Author: BobTheBuidler
Author-email: bobthebuidlerdefi@gmail.com
Requires-Python: >=3.10,<3.14
Classifier: License :: OSI Approved :: MIT License
Classifier: Programming Language :: Python :: 3
Classifier: Programming Language :: Python :: 3.10
Classifier: Programming Language :: Python :: 3.11
Classifier: Programming Language :: Python :: 3.12
Classifier: Programming Language :: Python :: 3.13
Requires-Dist: aiofiles
Requires-Dist: aiolimiter (>=1.2,<1.3)
Requires-Dist: cchecksum (>=0.0.3,<1)
Requires-Dist: eth-retry (>=0.3.1,<1)
Requires-Dist: eth-typing (>=4.2.0)
Requires-Dist: evmspec (>=0.4.6,<1)
Requires-Dist: ez-a-sync (>=0.33.10,<1)
Requires-Dist: faster-eth-abi (>=5.2.12)
Requires-Dist: faster-eth-utils (>=5.3.11)
Requires-Dist: faster-hexbytes (>1,<2)
Requires-Dist: multicall (>=0.6.2,<1)
Requires-Dist: typed-envs (>=0.2.1,<0.3)
Requires-Dist: web3 (>=5.27,!=5.29.*,!=5.30.*,!=5.31.1,!=5.31.2,<8)
Project-URL: Documentation, https://BobTheBuidler.github.io/dank_mids
Project-URL: Homepage, https://github.com/BobTheBuidler/dank_mids
Project-URL: Repository, https://github.com/BobTheBuidler/dank_mids
